Metadata-Version: 2.1
Name: Translinguer
Version: 0.0.3
Summary: Allows writing simple scripts to manage locale/translation files
Home-page: https://github.com/AivanF/Translinguer
Author: AivanF.
Author-email: projects@aivanf.com
Classifier: Development Status :: 4 - Beta
Classifier: Programming Language :: Python :: 3
Classifier: Operating System :: OS Independent
Classifier: Topic :: Utilities
Classifier: Topic :: Text Processing
Classifier: License :: Freely Distributable
